{
    "classes": [
        {
            "digit": "0",
            "TP": 173,
            "FP": 11,
            "FN": 2,
            "precision": 0.9402173913043478,
            "recall": 0.9885714285714285,
            "f1_score": 0.9637883008356546
        },
        {
            "digit": "1",
            "TP": 226,
            "FP": 10,
            "FN": 8,
            "precision": 0.9576271186440678,
            "recall": 0.9658119658119658,
            "f1_score": 0.9617021276595744
        },
        {
            "digit": "2",
            "TP": 192,
            "FP": 22,
            "FN": 27,
            "precision": 0.897196261682243,
            "recall": 0.8767123287671232,
            "f1_score": 0.8868360277136258
        },
        {
            "digit": "3",
            "TP": 182,
            "FP": 22,
            "FN": 25,
            "precision": 0.8921568627450981,
            "recall": 0.8792270531400966,
            "f1_score": 0.8856447688564477
        },
        {
            "digit": "4",
            "TP": 191,
            "FP": 22,
            "FN": 26,
            "precision": 0.8967136150234741,
            "recall": 0.880184331797235,
            "f1_score": 0.8883720930232557
        },
        {
            "digit": "5",
            "TP": 154,
            "FP": 24,
            "FN": 25,
            "precision": 0.8651685393258427,
            "recall": 0.8603351955307262,
            "f1_score": 0.8627450980392157
        },
        {
            "digit": "6",
            "TP": 163,
            "FP": 17,
            "FN": 15,
            "precision": 0.9055555555555556,
            "recall": 0.9157303370786517,
            "f1_score": 0.9106145251396648
        },
        {
            "digit": "7",
            "TP": 174,
            "FP": 27,
            "FN": 31,
            "precision": 0.8656716417910447,
            "recall": 0.848780487804878,
            "f1_score": 0.8571428571428571
        },
        {
            "digit": "8",
            "TP": 159,
            "FP": 29,
            "FN": 33,
            "precision": 0.8457446808510638,
            "recall": 0.828125,
            "f1_score": 0.8368421052631579
        },
        {
            "digit": "9",
            "TP": 167,
            "FP": 35,
            "FN": 27,
            "precision": 0.8267326732673267,
            "recall": 0.8608247422680413,
            "f1_score": 0.8434343434343435
        }
    ],
    "global": {
        "TP": 1781,
        "FP": 219,
        "FN": 219,
        "precision": 0.8905,
        "recall": 0.8905,
        "f1_score": 0.8905
    }
}